system_info/__init__.py
system_info/sysinfo.py
system_info-2.0.3.dist-info/licenses/LICENSE
system_info-2.0.3.dist-info/METADATA
system_info-2.0.3.dist-info/WHEEL
system_info-2.0.3.dist-info/top_level.txt
system_info-2.0.3.dist-info/RECORD
