Metadata-Version: 2.4
Name: system_info
Version: 2.0.3
Summary: Package for finding system hardware specifications
Home-page: https://github.com/suhanna/System_info
Author: Suhanna CH
Author-email: suhanna52@gmail.com
Classifier: Programming Language :: Python :: 3
Classifier: License :: OSI Approved :: MIT License
Classifier: Operating System :: OS Independent
Requires-Python: >=3.6
License-File: LICENSE
Requires-Dist: py-cpuinfo>=6.0.0
Requires-Dist: psutil
Dynamic: author
Dynamic: author-email
Dynamic: classifier
Dynamic: description
Dynamic: description-content-type
Dynamic: home-page
Dynamic: license-file
Dynamic: requires-dist
Dynamic: requires-python
Dynamic: summary
